datacleaning/__init__.py
datacleaning/datacleaning.py
data_cleaning-1.0.1.dist-info/LICENSE
data_cleaning-1.0.1.dist-info/METADATA
data_cleaning-1.0.1.dist-info/WHEEL
data_cleaning-1.0.1.dist-info/top_level.txt
data_cleaning-1.0.1.dist-info/RECORD
