Metadata-Version: 2.1
Name: data-cleaning
Version: 1.0.1
Summary: An utility to clean the data and return you the cleaned data
Home-page: https://github.com/DataPreprocessing/DataCleaning
Author: Murali krishna mopi devi, Induraj P.Ramamurthy
Author-email: mopidevi@gmail.com, induraj.gandhian@yahoo.com
License: UNKNOWN
Platform: UNKNOWN
Classifier: Development Status :: 3 - Alpha
Classifier: Intended Audience :: Science/Research
Classifier: License :: OSI Approved :: MIT License
Classifier: Natural Language :: English
Classifier: Operating System :: OS Independent
Classifier: Programming Language :: Python :: 3.6
Classifier: Programming Language :: Python :: 3.7
Classifier: Programming Language :: Python :: 3.8
Classifier: Topic :: Software Development :: Libraries :: Python Modules
Classifier: Topic :: Scientific/Engineering :: Artificial Intelligence
Requires-Python: >=3.6
Requires-Dist: missingpy
Requires-Dist: joblib
Requires-Dist: numpy
Requires-Dist: pandas
Requires-Dist: python-dateutil
Requires-Dist: pytz
Requires-Dist: scikit-learn
Requires-Dist: scipy
Requires-Dist: six
Requires-Dist: threadpoolctl
